kustosz/__init__.py
kustosz/admin.py
kustosz/apps.py
kustosz/asgi.py
kustosz/authentication.py
kustosz/celery.py
kustosz/cli/__init__.py
kustosz/cli/manage.py
kustosz/constants.py
kustosz/enums.py
kustosz/exceptions.py
kustosz/fetchers/__init__.py
kustosz/fetchers/feed.py
kustosz/fetchers/url.py
kustosz/filters.py
kustosz/forms/__init__.py
kustosz/forms/fields.py
kustosz/management/__init__.py
kustosz/management/commands/__init__.py
kustosz/management/commands/add_entry.py
kustosz/management/commands/export_channels.py
kustosz/management/commands/fetch_new_content.py
kustosz/management/commands/import_channels.py
kustosz/managers.py
kustosz/migrations/0001_initial.py
kustosz/migrations/0002_create_manual_channel_20210923_1906.py
kustosz/migrations/0003_create_celery_beat_20220108_0935.py
kustosz/migrations/0004_entry_mark_as_read_20220622_1219.py
kustosz/migrations/__init__.py
kustosz/models.py
kustosz/renderers.py
kustosz/serializers.py
kustosz/settings.py
kustosz/signals.py
kustosz/tasks/__init__.py
kustosz/tasks/task_add_channels.py
kustosz/tasks/task_add_readability_contents.py
kustosz/tasks/task_autodetect_channel_content_from_url.py
kustosz/tasks/task_autodetect_channels_from_url.py
kustosz/tasks/task_autodetect_content_from_url.py
kustosz/tasks/task_autodetect_entry_content_from_url.py
kustosz/tasks/task_clean_feed_fetcher_cache.py
kustosz/tasks/task_clean_url_fetcher_cache.py
kustosz/tasks/task_deduplicate_entries.py
kustosz/tasks/task_fetch_channel_content.py
kustosz/tasks/task_fetch_feed_channel_content.py
kustosz/tasks/task_fetch_manual_entry_data.py
kustosz/tasks/task_fetch_manual_entry_metadata.py
kustosz/tasks/task_filter_action_run_script.py
kustosz/tasks/task_run_filters_on_entries.py
kustosz/third_party/__init__.py
kustosz/third_party/taggit_serializer/__init__.py
kustosz/third_party/taggit_serializer/serializers.py
kustosz/types.py
kustosz/urls.py
kustosz/utils/__init__.py
kustosz/utils/autodetect_content.py
kustosz/utils/duplicate_finder.py
kustosz-23.8.0.dist-info/LICENSE
kustosz-23.8.0.dist-info/METADATA
kustosz-23.8.0.dist-info/WHEEL
kustosz-23.8.0.dist-info/entry_points.txt
kustosz-23.8.0.dist-info/RECORD
