Metadata-Version: 2.1
Name: kustosz
Version: 23.8.0
Summary: Focus on the worthwhile content with Kustosz, open source self-hosted web application. This package contains backend server.
Home-page: https://www.kustosz.org/
License: EUPL-1.2
Author: Mirek Długosz
Author-email: mirek@mirekdlugosz.com
Requires-Python: >=3.9,<4.0
Classifier: Development Status :: 5 - Production/Stable
Classifier: Environment :: Web Environment
Classifier: Framework :: Django
Classifier: Intended Audience :: End Users/Desktop
Classifier: Intended Audience :: Science/Research
Classifier: License :: OSI Approved :: European Union Public Licence 1.2 (EUPL 1.2)
Classifier: Operating System :: POSIX :: Linux
Classifier: Programming Language :: Python :: 3
Classifier: Programming Language :: Python :: 3.9
Classifier: Programming Language :: Python :: 3.10
Classifier: Programming Language :: Python :: 3.11
Classifier: Topic :: Internet :: WWW/HTTP :: WSGI :: Application
Provides-Extra: container
Provides-Extra: heroku
Provides-Extra: installer
Requires-Dist: Django (>=4.2,<5.0)
Requires-Dist: Unalix (>=0.9,<0.10)
Requires-Dist: celery (>=5.3.1,<6.0.0)
Requires-Dist: dacite (>=1.8.0,<2.0.0)
Requires-Dist: dj-database-url (>=2.0.0,<3.0.0) ; extra == "heroku"
Requires-Dist: django-celery-beat (>=2.5.0,<3.0.0)
Requires-Dist: django-celery-results (>=2.5.1,<3.0.0)
Requires-Dist: django-cors-headers (>=4.2.0,<5.0.0)
Requires-Dist: django-extensions (>=3.2.3,<4.0.0)
Requires-Dist: django-filter (>=23.2,<24.0)
Requires-Dist: django-taggit (>=4.0.0,<5.0.0)
Requires-Dist: django-taggit-serializer (>=0.1.7,<0.2.0)
Requires-Dist: djangorestframework (>=3.14.0,<4.0.0)
Requires-Dist: dynaconf (>=3.2.0,<4.0.0)
Requires-Dist: gunicorn (>=21.2.0,<22.0.0) ; extra == "container" or extra == "installer" or extra == "heroku"
Requires-Dist: hyperlink (>=21.0.0,<22.0.0)
Requires-Dist: listparser (>=0.19,<0.20)
Requires-Dist: psycopg2 (>=2.9.7,<3.0.0) ; extra == "container"
Requires-Dist: psycopg2-binary (>=2.9.7,<3.0.0) ; extra == "heroku"
Requires-Dist: readability-lxml (>=0.8.1,<0.9.0)
Requires-Dist: reader (>=3.7,<4.0)
Requires-Dist: redis (>=4.6.0,<5.0.0) ; extra == "container" or extra == "installer" or extra == "heroku"
Requires-Dist: requests-cache (>=1.1.0,<2.0.0)
Requires-Dist: supervisor (>=4.2.4,<5.0.0) ; extra == "heroku"
Requires-Dist: whitenoise (>=6.5.0,<7.0.0) ; extra == "container" or extra == "heroku"
Project-URL: Documentation, https://docs.kustosz.org/
Project-URL: Repository, https://github.com/KustoszApp/server/
